rigidbodysimulator/__init__.py
rigidbodysimulator/_version.py
rigidbodysimulator/plotting.py
rigidbodysimulator/rigid_body_dynamics.py
rigidbodysimulator/substitute_dynamic_symbols.py
rigidbodysimulator-0.2.7.dist-info/LICENSE
rigidbodysimulator-0.2.7.dist-info/METADATA
rigidbodysimulator-0.2.7.dist-info/WHEEL
rigidbodysimulator-0.2.7.dist-info/top_level.txt
rigidbodysimulator-0.2.7.dist-info/RECORD
