Metadata-Version: 2.1
Name: rigidbodysimulator
Version: 0.2.7
Summary: rigidbodysimulator simulator
Home-page: https://github.com/martinlarsalbert/motion-to-acceleration
Author: SSPA
Author-email: maa@sspa.se
License: UNKNOWN
Platform: UNKNOWN
Classifier: Programming Language :: Python :: 3
Classifier: Operating System :: OS Independent
Requires-Python: >=3.5
Requires-Dist: sympy
Requires-Dist: pandas
Requires-Dist: matplotlib
Requires-Dist: pydy
Requires-Dist: pytest
Requires-Dist: versioneer
Requires-Dist: wheel
Provides-Extra: dev
Requires-Dist: wheel ; extra == 'dev'
Requires-Dist: versioneer ; extra == 'dev'
Provides-Extra: plot
Requires-Dist: ipvolume ; extra == 'plot'
Requires-Dist: ipywidgets ; extra == 'plot'
